spectacularAI_native.cpython-39-x86_64-linux-gnu.so
spectacularAI/__init__.py
spectacularAI/run_sai_cli.py
spectacularAI/cli/__init__.py
spectacularAI/cli/sai_cli.py
spectacularAI/cli/smooth.py
spectacularAI/cli/calibrate/__init__.py
spectacularAI/cli/calibrate/calibrate.py
spectacularAI/cli/calibrate/html.py
spectacularAI/cli/calibrate/report.py
spectacularAI/cli/calibrate_frd/__init__.py
spectacularAI/cli/calibrate_frd/calibrate_frd.py
spectacularAI/cli/convert/__init__.py
spectacularAI/cli/convert/binary.py
spectacularAI/cli/convert/convert.py
spectacularAI/cli/convert/tum.py
spectacularAI/cli/diagnose/__init__.py
spectacularAI/cli/diagnose/diagnose.py
spectacularAI/cli/diagnose/gnss.py
spectacularAI/cli/diagnose/html.py
spectacularAI/cli/diagnose/sensors.py
spectacularAI/cli/process/__init__.py
spectacularAI/cli/process/process.py
spectacularAI/cli/record/__init__.py
spectacularAI/cli/record/oak.py
spectacularAI/cli/record/record.py
spectacularAI/cli/visualization/__init__.py
spectacularAI/cli/visualization/serialization.py
spectacularAI/cli/visualization/vio_visu.py
spectacularAI/cli/visualization/visualizer.py
spectacularAI/cli/visualization/visualizer_renderers/__init__.py
spectacularAI/cli/visualization/visualizer_renderers/mesh.frag
spectacularAI/cli/visualization/visualizer_renderers/mesh.py
spectacularAI/cli/visualization/visualizer_renderers/mesh.vert
spectacularAI/cli/visualization/visualizer_renderers/point_cloud.frag
spectacularAI/cli/visualization/visualizer_renderers/point_cloud.py
spectacularAI/cli/visualization/visualizer_renderers/point_cloud.vert
spectacularAI/cli/visualization/visualizer_renderers/renderers.py
spectacularAI/cli/visualization/visualizer_renderers/util.py
spectacularai-1.49.0.dist-info/METADATA
spectacularai-1.49.0.dist-info/WHEEL
spectacularai-1.49.0.dist-info/entry_points.txt
spectacularai-1.49.0.dist-info/top_level.txt
spectacularai-1.49.0.dist-info/RECORD
spectacularai-1.49.0.dist-info/licenses/LICENSE.txt
