Metadata-Version: 2.4
Name: spectacularai
Version: 1.49.0
Summary: Spectacular AI Python library
Home-page: https://github.com/SpectacularAI/sdk-examples
Author: Spectacular AI Ltd
Author-email: apps@spectacularai.com
License: Free for non-commercial use
Keywords: vio slam
Classifier: Development Status :: 4 - Beta
Classifier: Intended Audience :: Science/Research
Classifier: Topic :: Scientific/Engineering :: Artificial Intelligence
Classifier: License :: Free for non-commercial use
Classifier: Operating System :: Microsoft :: Windows
Classifier: Operating System :: Unix
Classifier: Programming Language :: Python :: 3
Classifier: Programming Language :: Python :: 3.8
Classifier: Programming Language :: Python :: 3.9
Classifier: Programming Language :: Python :: 3.10
Classifier: Programming Language :: Python :: 3.11
Classifier: Programming Language :: Python :: 3.12
Classifier: Programming Language :: C++
Classifier: Programming Language :: Python :: Implementation :: CPython
Requires-Python: >=3
License-File: LICENSE.txt
Requires-Dist: depthai==2.28.0
Requires-Dist: numpy<2,>=1
Provides-Extra: visualization
Requires-Dist: pyopengl; extra == "visualization"
Requires-Dist: pygame; extra == "visualization"
Provides-Extra: cli
Requires-Dist: opencv-python; extra == "cli"
Requires-Dist: pandas; extra == "cli"
Requires-Dist: pyyaml; extra == "cli"
Requires-Dist: matplotlib; extra == "cli"
Requires-Dist: scipy; extra == "cli"
Provides-Extra: full
Requires-Dist: pyopengl; extra == "full"
Requires-Dist: pygame; extra == "full"
Requires-Dist: opencv-python; extra == "full"
Requires-Dist: pandas; extra == "full"
Requires-Dist: pyyaml; extra == "full"
Requires-Dist: matplotlib; extra == "full"
Requires-Dist: scipy; extra == "full"
Dynamic: author
Dynamic: author-email
Dynamic: classifier
Dynamic: description
Dynamic: home-page
Dynamic: keywords
Dynamic: license
Dynamic: license-file
Dynamic: provides-extra
Dynamic: requires-dist
Dynamic: requires-python
Dynamic: summary
